{
    "name":"Minecraft",

    "field":{
        "pos":[480, 360],
        "width":880,
        "height":520,
        "decal":"pictures/background.png",
        "type":"horizontal"
    },

    "player1":{
        "pos1":[360, 360],
        "pos2":[360, 840],
        "decal":"pictures/paddle.png"
    },

    "player2":{
        "pos1":[1440, 360],
        "pos2":[1440, 840],
        "decal":"pictures/paddle.png"
    },

    "ball":{
        "decal":"pictures/ball.png"
        
    },

    "score":{
        "pos":[960, 180],
        "font_size":200,
        "color":"Black",
        "font":"fonts/font.ttf"
    }
}